README.md
setup.py
cameo_botrun_prompt_tools/__init__.py
cameo_botrun_prompt_tools/cameo_botrun_prompt_tools.py
cameo_botrun_prompt_tools.egg-info/PKG-INFO
cameo_botrun_prompt_tools.egg-info/SOURCES.txt
cameo_botrun_prompt_tools.egg-info/dependency_links.txt
cameo_botrun_prompt_tools.egg-info/requires.txt
cameo_botrun_prompt_tools.egg-info/top_level.txt