Metadata-Version: 2.1
Name: cameo-botrun-prompt-tools
Version: 1.0.3
Summary: cameo_botrun_prompt_tools
Home-page: https://github.com/bohachu/cameo_botrun_prompt_tools
Author: elantievs
Author-email: elantievs@gmail.com
License: UNKNOWN
Platform: UNKNOWN
Classifier: Programming Language :: Python :: 3
Classifier: License :: OSI Approved :: MIT License
Classifier: Operating System :: OS Independent
Requires-Python: >=3.11
